dataheroes/__init__.cp39-win_amd64.pyd
dataheroes/cli.cp39-win_amd64.pyd
dataheroes/common.cp39-win_amd64.pyd
dataheroes/configuration.cp39-win_amd64.pyd
dataheroes/utils.cp39-win_amd64.pyd
dataheroes/vendor_utils.cp39-win_amd64.pyd
dataheroes/version.cp39-win_amd64.pyd
dataheroes/version_type.cp39-win_amd64.pyd
dataheroes/core/__init__.cp39-win_amd64.pyd
dataheroes/core/common.cp39-win_amd64.pyd
dataheroes/core/helpers.cp39-win_amd64.pyd
dataheroes/core/numpy_extra.cp39-win_amd64.pyd
dataheroes/core/types.cp39-win_amd64.pyd
dataheroes/core/coreset/__init__.cp39-win_amd64.pyd
dataheroes/core/coreset/_base.cp39-win_amd64.pyd
dataheroes/core/coreset/common.cp39-win_amd64.pyd
dataheroes/core/coreset/coreset_analytics.cp39-win_amd64.pyd
dataheroes/core/coreset/coreset_dtc.cp39-win_amd64.pyd
dataheroes/core/coreset/coreset_dtr.cp39-win_amd64.pyd
dataheroes/core/coreset/coreset_gmm.cp39-win_amd64.pyd
dataheroes/core/coreset/coreset_kmeans.cp39-win_amd64.pyd
dataheroes/core/coreset/coreset_lg.cp39-win_amd64.pyd
dataheroes/core/coreset/coreset_nmf.cp39-win_amd64.pyd
dataheroes/core/coreset/coreset_pca.cp39-win_amd64.pyd
dataheroes/core/coreset/coreset_qda.cp39-win_amd64.pyd
dataheroes/core/coreset/coreset_reg.cp39-win_amd64.pyd
dataheroes/core/coreset/coreset_svd.cp39-win_amd64.pyd
dataheroes/core/coreset/coreset_svm.cp39-win_amd64.pyd
dataheroes/core/coreset/coreset_uniform.cp39-win_amd64.pyd
dataheroes/core/coreset/exceptions.cp39-win_amd64.pyd
dataheroes/core/estimator/__init__.cp39-win_amd64.pyd
dataheroes/core/estimator/_base.cp39-win_amd64.pyd
dataheroes/core/estimator/lightweight.cp39-win_amd64.pyd
dataheroes/core/estimator/unified.cp39-win_amd64.pyd
dataheroes/core/estimator/uniform.cp39-win_amd64.pyd
dataheroes/core/sklearn_extra/__init__.cp39-win_amd64.pyd
dataheroes/core/sklearn_extra/_target_encoder.cp39-win_amd64.pyd
dataheroes/core/sklearn_extra/_target_encoder_fast.cp39-win_amd64.pyd
dataheroes/core/sklearn_extra/array_encoder.cp39-win_amd64.pyd
dataheroes-0.17.0.dist-info/licenses/LICENSE
dataheroes-0.17.0.dist-info/METADATA
dataheroes-0.17.0.dist-info/WHEEL
dataheroes-0.17.0.dist-info/entry_points.txt
dataheroes-0.17.0.dist-info/top_level.txt
dataheroes-0.17.0.dist-info/RECORD
